[
    {
        "id": "a5a36667-2cba-4d43-9ef2-372d9e5e75ee",
        "name": "Молочный коктейль 300мл",
        "price_for_mid": 120,
        "img": "yj2qmGLr6t8.webp",
        "countByMid": 0,
        "countByLarge": 0,
        "select": "large"
    },
    {
        "id": "1375ca85-1ba1-4be5-bce1-9ace9751cc6b",
        "name": "Сок детский 200мл",
        "price_for_mid": 40,
        "img": "yj2qmGLr6t8.webp",
        "countByMid": 0,
        "countByLarge": 0,
        "select": "large"
    },
    {
        "id": "28de54de-4e54-4ba0-b9e6-042f38116b02",
        "name": "Coca-cola classic 0,5",
        "price_for_mid": 85,
        "img": "Vkpf8mSRyNY.webp",
        "countByMid": 0,
        "countByLarge": 0,
        "select": "large"
    },
    {
        "id": "22b26f3f-7e3b-469a-869d-c4e0c1ce99af",
        "name": "Coca-cola zero 1",
        "price_for_mid": 120,
        "img": "Vkpf8mSRyNY.webp",
        "countByMid": 0,
        "countByLarge": 0,
        "select": "large"
    },
    {
        "id": "cd6ec834-c75e-4ca6-b586-fb911205ff92",
        "name": "Coca-cola classic 1,5",
        "price_for_mid": 150,
        "img": "Vkpf8mSRyNY.webp",
        "countByMid": 0,
        "countByLarge": 0,
        "select": "large"
    },
    {
        "id": "37e8db91-62e9-4209-9617-0ee1323b5a96",
        "name": "Эспрессо 60мл",
        "price_for_mid": 80,
        "img": "aqTC7uD-0Kk.webp",
        "countByMid": 0,
        "countByLarge": 0,
        "select": "large"
    },
    {
        "id": "fd4d98c9-7341-4127-b87b-fc331bfd964e",
        "name": "Капучино 200мл",
        "price_for_mid": 150,
        "img": "aqTC7uD-0Kk.webp",
        "countByMid": 0,
        "countByLarge": 0,
        "select": "large"
    },
    {
        "id": "67b1de4a-9a93-4465-adfc-96413623150f",
        "name": "Латте 200мл",
        "price_for_mid": 180,
        "img": "aqTC7uD-0Kk.webp",
        "countByMid": 0,
        "countByLarge": 0,
        "select": "large"
    }
]